setup.py
hkshiteshpkg/__init__.py
hkshiteshpkg/calculator.py
hkshiteshpkg.egg-info/PKG-INFO
hkshiteshpkg.egg-info/SOURCES.txt
hkshiteshpkg.egg-info/dependency_links.txt
hkshiteshpkg.egg-info/requires.txt
hkshiteshpkg.egg-info/top_level.txt