Metadata-Version: 2.1
Name: hkshiteshpkg
Version: 0.0.1
Summary: limeguru python module
Home-page: https://github.com/hkshitesh/hkshiteshpkg
Author: hkshitesh
Author-email: hkshitesh@gmail.com
Classifier: Programming Language :: Python :: 3
Classifier: Operating System :: OS Independent
